[
  {
    "name": "Пенни",
    "description": "Пенни стреляет мешочками с монетами. Они наносят урон цели и любому, кто находится за ней. Её Супер — бронебашня-мортира!",
    "attack": {
      "name": "Мушкетон",
      "descr": "«Стреляет мешочком фальшивого золота. Задев врага, мешочек рвётся и осыпает монетами тех, кто находится позади.»"
    },
    "super": {
      "name": "Старый пройдоха",
      "descr": "«Пенни устанавливает пушку, которая достаёт врагов на большой дистанции, даже если они в укрытии.»"
    },
    "amplification": [
      {
        "name": "Прощальный залп",
        "descr": "«При уничтожении пушка Пенни даёт залп из 4 бомб по врагам, находящимся поблизости. Каждая бомба наносит 1680 очков урона.»"
      },
      {
        "name": "Защитный пируэт",
        "descr": "«Ядра из пушки Пенни поджигают землю на 3 секунды. Враги в зоне пожара теряют 400 очков здоровья в секунду! »"
      }
    ],
    "gadget": [
      {
        "name": "Карманный детонатор",
        "descr": "«Пенни взрывает свою пушку, разрушая стены и нанося 1500 ед. урона врагам, находящимся поблизости. Зарядов на матч: 3.»"
      },
      {
        "name": "Капитанский компас",
        "descr": "«Пушка стреляет туда, где находится Пенни. Зарядов на матч: 3.»"
      }
    ]
  }
]